sherlockpipe/__init__.py
sherlockpipe/__main__.py
sherlockpipe/constants.py
sherlockpipe/exomoon.py
sherlockpipe/fit.py
sherlockpipe/maxsector.py
sherlockpipe/moriarty.py
sherlockpipe/plan.py
sherlockpipe/properties.yaml
sherlockpipe/service.py
sherlockpipe/stability.py
sherlockpipe/tidal.py
sherlockpipe/ttvs.py
sherlockpipe/update.py
sherlockpipe/vet.py
sherlockpipe/bayesian_fit/__init__.py
sherlockpipe/bayesian_fit/allesfitter_data_extractor.py
sherlockpipe/bayesian_fit/fit_report.py
sherlockpipe/bayesian_fit/fitter.py
sherlockpipe/bayesian_fit/run.py
sherlockpipe/catalog/__init__.py
sherlockpipe/catalog/mast.py
sherlockpipe/ellc/.git
sherlockpipe/ellc/.gitignore
sherlockpipe/ellc/CHANGELOG.rst
sherlockpipe/ellc/LICENSE.txt
sherlockpipe/ellc/MANIFEST.in
sherlockpipe/ellc/README.txt
sherlockpipe/ellc/makefile
sherlockpipe/ellc/requirements.txt
sherlockpipe/ellc/setup.cfg
sherlockpipe/ellc/setup.py
sherlockpipe/ellc/bin/ellc_emcee
sherlockpipe/ellc/data/g_Claret2004.fits
sherlockpipe/ellc/data/g_Claret2011.fits
sherlockpipe/ellc/ellc/__init__.py
sherlockpipe/ellc/ellc/fluxes.py
sherlockpipe/ellc/ellc/lc.py
sherlockpipe/ellc/ellc/ldy.py
sherlockpipe/ellc/ellc/rv.py
sherlockpipe/ellc/ellc/version.py
sherlockpipe/ellc/f_src/constants.f90
sherlockpipe/ellc/f_src/coords.f90
sherlockpipe/ellc/f_src/ellc.f90
sherlockpipe/ellc/f_src/ellc.f90.save
sherlockpipe/ellc/f_src/ellipse.f90
sherlockpipe/ellc/f_src/gauss_legendre.f90
sherlockpipe/ellc/f_src/solve_real_poly.f90
sherlockpipe/ellc/f_src/spots.f90
sherlockpipe/ellc/f_src/stellar.f90
sherlockpipe/ellc/f_src/utils.f90
sherlockpipe/ellc/test/test_lc_rv.py
sherlockpipe/loading/__init__.py
sherlockpipe/loading/common.py
sherlockpipe/loading/tool_with_candidate.py
sherlockpipe/observation_plan/__init__.py
sherlockpipe/observation_plan/observation_report.py
sherlockpipe/observation_plan/planner.py
sherlockpipe/observation_plan/run.py
sherlockpipe/ois/OisManager.py
sherlockpipe/ois/__init__.py
sherlockpipe/plot/__init__.py
sherlockpipe-1.4.0.dist-info/licenses/LICENSE
sherlockpipe-1.4.0.dist-info/METADATA
sherlockpipe-1.4.0.dist-info/WHEEL
sherlockpipe-1.4.0.dist-info/top_level.txt
sherlockpipe-1.4.0.dist-info/RECORD
