Metadata-Version: 2.4
Name: sherlockpipe
Version: 1.4.0
Summary: Search for Hints of Exoplanets fRom Lightcurves Of spaCe based seeKers
Home-page: https://github.com/franpoz/SHERLOCK
Author: M. Dévora-Pajares & F.J. Pozuelos
Author-email: mdevorapajares@protonmail.com
Classifier: Programming Language :: Python :: 3
Classifier: License :: OSI Approved :: MIT License
Classifier: Operating System :: OS Independent
Requires-Python: >=3.11
License-File: LICENSE
Requires-Dist: astroplan==0.10.1
Requires-Dist: alexfitter==1.2.19
Requires-Dist: argparse==1.4.0
Requires-Dist: celerite==0.4.3
Requires-Dist: corner==2.2.3
Requires-Dist: dearwatson==1.0.1
Requires-Dist: dynesty==2.1.5
Requires-Dist: emcee==3.1.6
Requires-Dist: mock==4.0.3
Requires-Dist: pytz
Requires-Dist: requests==2.32.3
Requires-Dist: rebound==4.4.1
Requires-Dist: reproject==0.13.0
Requires-Dist: seaborn==0.13.2
Requires-Dist: setuptools>=41.0.0
Requires-Dist: sklearn==0.0
Requires-Dist: statsmodels==0.13.5
Requires-Dist: timezonefinder==5.2.0
Requires-Dist: tqdm==4.56.0
Dynamic: author
Dynamic: author-email
Dynamic: classifier
Dynamic: description
Dynamic: description-content-type
Dynamic: home-page
Dynamic: license-file
Dynamic: requires-dist
Dynamic: requires-python
Dynamic: summary
